googleDriveFileDownloader/__init__.py
googleDriveFileDownloader/googleDriveFileDownloader.py
googleDriveFileDownloader-1.2.dist-info/LICENSE
googleDriveFileDownloader-1.2.dist-info/METADATA
googleDriveFileDownloader-1.2.dist-info/WHEEL
googleDriveFileDownloader-1.2.dist-info/top_level.txt
googleDriveFileDownloader-1.2.dist-info/RECORD
